{
  "within_event_time": {
    "1": {
      "rows_train": 41025,
      "rows_test": 12842,
      "auc": 0.6576955312210755,
      "brier": 0.21410297149330698,
      "pr_auc": 0.5179988384425839,
      "event_count": 1,
      "train_ratio": 0.8001182916199726,
      "pos_rate_train": 0.3404021937842779,
      "class_strategy": "none"
    },
    "2": {
      "rows_train": 41025,
      "rows_test": 12842,
      "auc": 0.6607756646506421,
      "brier": 0.23621820171178004,
      "pr_auc": 0.6198742167865947,
      "event_count": 1,
      "train_ratio": 0.8001182916199726,
      "pos_rate_train": 0.460938452163315,
      "class_strategy": "none"
    },
    "4": {
      "rows_train": 41025,
      "rows_test": 12842,
      "auc": 0.6753791124677782,
      "brier": 0.2368161059673871,
      "pr_auc": 0.7231359222044978,
      "event_count": 1,
      "train_ratio": 0.8001182916199726,
      "pos_rate_train": 0.5770871419865935,
      "class_strategy": "none"
    },
    "8": {
      "rows_train": 41025,
      "rows_test": 12842,
      "auc": 0.6895055120095582,
      "brier": 0.22295129873183084,
      "pr_auc": 0.7966825729724366,
      "event_count": 1,
      "train_ratio": 0.8001182916199726,
      "pos_rate_train": 0.6825106642291285,
      "class_strategy": "none"
    }
  },
  "groupkfold_event": {
    "1": {
      "rows_train": 64248,
      "rows_test": 0,
      "auc": null,
      "brier": null,
      "pr_auc": null,
      "event_count": 1,
      "folds": 0,
      "note": "insufficient training data"
    },
    "2": {
      "rows_train": 64248,
      "rows_test": 0,
      "auc": null,
      "brier": null,
      "pr_auc": null,
      "event_count": 1,
      "folds": 0,
      "note": "insufficient training data"
    },
    "4": {
      "rows_train": 64248,
      "rows_test": 0,
      "auc": null,
      "brier": null,
      "pr_auc": null,
      "event_count": 1,
      "folds": 0,
      "note": "insufficient training data"
    },
    "8": {
      "rows_train": 64248,
      "rows_test": 0,
      "auc": null,
      "brier": null,
      "pr_auc": null,
      "event_count": 1,
      "folds": 0,
      "note": "insufficient training data"
    }
  },
  "calibration": {
    "1": {
      "rows": 10381,
      "brier": 0.21639008977888494,
      "ece": 5.2116901809810864e-17,
      "method": "isotonic"
    },
    "2": {
      "rows": 10381,
      "brier": 0.20811690694662163,
      "ece": 1.4288199218757433e-17,
      "method": "isotonic"
    },
    "4": {
      "rows": 10381,
      "brier": 0.18737910025563698,
      "ece": 2.6827805194800166e-17,
      "method": "isotonic"
    },
    "8": {
      "rows": 10381,
      "brier": 0.14744528719323094,
      "ece": 4.830823044246057e-17,
      "method": "isotonic"
    }
  },
  "ranking": {
    "1": {
      "rows_test": 12842,
      "overall": [
        {
          "k": 10,
          "precision": 1.0,
          "recall": 0.0021710811984368217,
          "total_positives": 4606
        },
        {
          "k": 25,
          "precision": 0.96,
          "recall": 0.005210594876248371,
          "total_positives": 4606
        },
        {
          "k": 50,
          "precision": 0.94,
          "recall": 0.01020408163265306,
          "total_positives": 4606
        },
        {
          "k": 100,
          "precision": 0.87,
          "recall": 0.01888840642640035,
          "total_positives": 4606
        }
      ],
      "priority_1": [
        {
          "k": 10,
          "precision": 0.8,
          "recall": 0.0025340513145391194,
          "total_positives": 3157
        },
        {
          "k": 25,
          "precision": 0.88,
          "recall": 0.006968641114982578,
          "total_positives": 3157
        },
        {
          "k": 50,
          "precision": 0.76,
          "recall": 0.012036743744060817,
          "total_positives": 3157
        },
        {
          "k": 100,
          "precision": 0.79,
          "recall": 0.025023756731073803,
          "total_positives": 3157
        }
      ],
      "other": [
        {
          "k": 10,
          "precision": 0.9,
          "recall": 0.006211180124223602,
          "total_positives": 1449
        },
        {
          "k": 25,
          "precision": 0.96,
          "recall": 0.016563146997929608,
          "total_positives": 1449
        },
        {
          "k": 50,
          "precision": 0.96,
          "recall": 0.033126293995859216,
          "total_positives": 1449
        },
        {
          "k": 100,
          "precision": 0.87,
          "recall": 0.060041407867494824,
          "total_positives": 1449
        }
      ]
    },
    "2": {
      "rows_test": 12842,
      "overall": [
        {
          "k": 10,
          "precision": 1.0,
          "recall": 0.0017208742040956805,
          "total_positives": 5811
        },
        {
          "k": 25,
          "precision": 0.92,
          "recall": 0.003958010669420065,
          "total_positives": 5811
        },
        {
          "k": 50,
          "precision": 0.9,
          "recall": 0.007743933918430563,
          "total_positives": 5811
        },
        {
          "k": 100,
          "precision": 0.88,
          "recall": 0.015143692996041989,
          "total_positives": 5811
        }
      ],
      "priority_1": [
        {
          "k": 10,
          "precision": 0.8,
          "recall": 0.0019689884321929607,
          "total_positives": 4063
        },
        {
          "k": 25,
          "precision": 0.72,
          "recall": 0.004430223972434162,
          "total_positives": 4063
        },
        {
          "k": 50,
          "precision": 0.78,
          "recall": 0.009598818606940684,
          "total_positives": 4063
        },
        {
          "k": 100,
          "precision": 0.73,
          "recall": 0.01796701944376077,
          "total_positives": 4063
        }
      ],
      "other": [
        {
          "k": 10,
          "precision": 1.0,
          "recall": 0.005720823798627002,
          "total_positives": 1748
        },
        {
          "k": 25,
          "precision": 0.92,
          "recall": 0.013157894736842105,
          "total_positives": 1748
        },
        {
          "k": 50,
          "precision": 0.96,
          "recall": 0.02745995423340961,
          "total_positives": 1748
        },
        {
          "k": 100,
          "precision": 0.97,
          "recall": 0.055491990846681924,
          "total_positives": 1748
        }
      ]
    },
    "4": {
      "rows_test": 12842,
      "overall": [
        {
          "k": 10,
          "precision": 0.9,
          "recall": 0.0012796815014929617,
          "total_positives": 7033
        },
        {
          "k": 25,
          "precision": 0.96,
          "recall": 0.0034124840039812315,
          "total_positives": 7033
        },
        {
          "k": 50,
          "precision": 0.98,
          "recall": 0.00696715484146168,
          "total_positives": 7033
        },
        {
          "k": 100,
          "precision": 0.97,
          "recall": 0.013792122849424143,
          "total_positives": 7033
        }
      ],
      "priority_1": [
        {
          "k": 10,
          "precision": 0.9,
          "recall": 0.0018068660911463562,
          "total_positives": 4981
        },
        {
          "k": 25,
          "precision": 0.96,
          "recall": 0.004818309576390283,
          "total_positives": 4981
        },
        {
          "k": 50,
          "precision": 0.94,
          "recall": 0.009435856253764304,
          "total_positives": 4981
        },
        {
          "k": 100,
          "precision": 0.96,
          "recall": 0.019273238305561134,
          "total_positives": 4981
        }
      ],
      "other": [
        {
          "k": 10,
          "precision": 0.9,
          "recall": 0.0043859649122807015,
          "total_positives": 2052
        },
        {
          "k": 25,
          "precision": 0.96,
          "recall": 0.011695906432748537,
          "total_positives": 2052
        },
        {
          "k": 50,
          "precision": 0.98,
          "recall": 0.02387914230019493,
          "total_positives": 2052
        },
        {
          "k": 100,
          "precision": 0.98,
          "recall": 0.04775828460038986,
          "total_positives": 2052
        }
      ]
    },
    "8": {
      "rows_test": 12842,
      "overall": [
        {
          "k": 10,
          "precision": 1.0,
          "recall": 0.0012266928361138372,
          "total_positives": 8152
        },
        {
          "k": 25,
          "precision": 0.96,
          "recall": 0.002944062806673209,
          "total_positives": 8152
        },
        {
          "k": 50,
          "precision": 0.98,
          "recall": 0.006010794896957802,
          "total_positives": 8152
        },
        {
          "k": 100,
          "precision": 0.98,
          "recall": 0.012021589793915604,
          "total_positives": 8152
        }
      ],
      "priority_1": [
        {
          "k": 10,
          "precision": 1.0,
          "recall": 0.0017415534656913968,
          "total_positives": 5742
        },
        {
          "k": 25,
          "precision": 0.88,
          "recall": 0.0038314176245210726,
          "total_positives": 5742
        },
        {
          "k": 50,
          "precision": 0.9,
          "recall": 0.007836990595611285,
          "total_positives": 5742
        },
        {
          "k": 100,
          "precision": 0.92,
          "recall": 0.01602229188436085,
          "total_positives": 5742
        }
      ],
      "other": [
        {
          "k": 10,
          "precision": 1.0,
          "recall": 0.004149377593360996,
          "total_positives": 2410
        },
        {
          "k": 25,
          "precision": 1.0,
          "recall": 0.01037344398340249,
          "total_positives": 2410
        },
        {
          "k": 50,
          "precision": 1.0,
          "recall": 0.02074688796680498,
          "total_positives": 2410
        },
        {
          "k": 100,
          "precision": 0.96,
          "recall": 0.03983402489626556,
          "total_positives": 2410
        }
      ]
    }
  },
  "eta_regression": {
    "rows_train": 50211,
    "rows_test": 9561,
    "mae": 5.910065218174763,
    "rmse": 7.729650205293286,
    "eta_class_mae": 3.1501254875992153,
    "eta_class_rmse": 5.663245818909643
  },
  "thresholds": {
    "1": {
      "threshold": 0.3089579524680072,
      "f1": 0.6018961322258579,
      "rows": 10381,
      "pos_rate": 0.39610827473268473,
      "metric": "f1"
    },
    "2": {
      "threshold": 0.38857142857142857,
      "f1": 0.722,
      "rows": 10381,
      "pos_rate": 0.5320296695886716,
      "metric": "f1"
    },
    "4": {
      "threshold": 0.43884892086330934,
      "f1": 0.7977192866140688,
      "rows": 10381,
      "pos_rate": 0.6426163182737694,
      "metric": "f1"
    },
    "8": {
      "threshold": 0.43548387096774194,
      "f1": 0.8608353404217823,
      "rows": 10381,
      "pos_rate": 0.7375012041229169,
      "metric": "f1"
    }
  },
  "feature_importance_path": "/home/runner/work/snow_map_dashboard/snow_map_dashboard/data/artifacts_snow/feature_importance.json"
}